{"MA150":{"tags":["Diode","Si"],"have":false,"want":true,"used":false,"spotted":true,"lookedup":true},"1N4001":{"tags":["Diode","Si"],"have":true,"want":false,"used":true,"spotted":true,"lookedup":true},"1A-GH":{"tags":["Diode","Si"],"have":false,"want":true,"used":false,"spotted":false,"lookedup":true},"1S310":{"tags":["Diode","Si"],"have":false,"want":true,"used":false,"spotted":false,"lookedup":true},"BY188B":{"tags":["Diode","Si"],"have":false,"want":true,"used":false,"spotted":false,"lookedup":true},"SE30":{"tags":["Diode","Si"],"have":false,"want":true,"used":false,"spotted":false,"lookedup":true},"VO-6C":{"tags":["Diode","Si"],"have":false,"want":true,"used":false,"spotted":false,"lookedup":true},"EM501":{"tags":["Diode","Si"],"have":false,"want":true,"used":false,"spotted":false,"lookedup":true},"1S1941":{"tags":["Diode","Si"],"have":false,"want":true,"used":false,"spotted":false,"lookedup":true},"AD4002":{"tags":["Diode","Si"],"have":false,"want":true,"used":false,"spotted":false,"lookedup":true},"DS130":{"tags":["Diode","Si"],"have":false,"want":true,"used":false,"spotted":false,"lookedup":true},"\u041a\u0414243\u0411":{"tags":["Diode","Si"],"have":false,"want":true,"used":false,"spotted":false,"lookedup":true},"1N4003":{"tags":["Diode","Si"],"have":false,"want":true,"used":false,"spotted":true,"lookedup":true},"EM502":{"tags":["Diode","Si"],"have":false,"want":true,"used":false,"spotted":false,"lookedup":true},"1N2482":{"tags":["Diode","Si"],"have":false,"want":true,"used":false,"spotted":false,"lookedup":true},"1N3193":{"tags":["Diode","Si"],"have":false,"want":true,"used":false,"spotted":false,"lookedup":true},"1N325":{"tags":["Diode","Si"],"have":false,"want":true,"used":false,"spotted":false,"lookedup":true},"1S1942":{"tags":["Diode","Si"],"have":false,"want":true,"used":false,"spotted":false,"lookedup":true},"AD4003":{"tags":["Diode","Si"],"have":false,"want":true,"used":false,"spotted":false,"lookedup":true},"EM402":{"tags":["Diode","Si"],"have":false,"want":true,"used":false,"spotted":false,"lookedup":true},"UF4003":{"tags":["Diode","Si"],"have":false,"want":true,"used":false,"spotted":false,"lookedup":true},"1N4004":{"tags":["Diode","Si"],"have":false,"want":true,"used":false,"spotted":false,"lookedup":true},"EM504":{"tags":["Diode","Si"],"have":false,"want":true,"used":false,"spotted":false,"lookedup":true},"1N3194":{"tags":["Diode","Si"],"have":false,"want":true,"used":false,"spotted":false,"lookedup":true},"1N4365":{"tags":["Diode","Si"],"have":false,"want":true,"used":false,"spotted":false,"lookedup":true},"1N1169":{"tags":["Diode","Si"],"have":false,"want":true,"used":false,"spotted":false,"lookedup":true},"1S1943":{"tags":["Diode","Si"],"have":false,"want":true,"used":false,"spotted":false,"lookedup":true},"AD4004":{"tags":["Diode","Si"],"have":false,"want":true,"used":false,"spotted":false,"lookedup":true},"DX0043TA":{"tags":["Diode","Si"],"have":false,"want":true,"used":false,"spotted":false,"lookedup":true},"EM404":{"tags":["Diode","Si"],"have":false,"want":true,"used":false,"spotted":false,"lookedup":true},"MO53":{"tags":["Diode","Si"],"have":false,"want":true,"used":false,"spotted":false,"lookedup":true},"BA159":{"tags":["Diode","Si"],"have":false,"want":true,"used":false,"spotted":false,"lookedup":true},"1N4007":{"tags":["Diode","Si"],"have":true,"want":false,"used":false,"spotted":false,"lookedup":true},"EM510":{"tags":["Diode","Si"],"have":false,"want":true,"used":false,"spotted":false,"lookedup":true},"10D10":{"tags":["Diode","Si"],"have":false,"want":true,"used":false,"spotted":false,"lookedup":true},"1N328":{"tags":["Diode","Si"],"have":false,"want":true,"used":false,"spotted":false,"lookedup":true},"F111":{"tags":["Diode","Si"],"have":false,"want":true,"used":false,"spotted":false,"lookedup":true},"TD184":{"tags":["Diode","Si"],"have":false,"want":true,"used":false,"spotted":false,"lookedup":true},"BY127":{"tags":["Diode","Si"],"have":false,"want":true,"used":false,"spotted":false,"lookedup":true},"BY103":{"tags":["Diode","Si"],"have":false,"want":true,"used":false,"spotted":false,"lookedup":true},"BY100":{"tags":["Diode","Si"],"have":false,"want":true,"used":false,"spotted":false,"lookedup":true},"OA211":{"tags":["Diode","Si"],"have":false,"want":true,"used":false,"spotted":false,"lookedup":true},"OA214":{"tags":["Diode","Si"],"have":false,"want":true,"used":false,"spotted":false,"lookedup":true},"XI64":{"tags":["Diode","Si"],"have":false,"want":true,"used":false,"spotted":false,"lookedup":true},"BY104":{"tags":["Diode","Si"],"have":false,"want":true,"used":false,"spotted":false,"lookedup":true},"BY133":{"tags":["Diode","Si"],"have":false,"want":true,"used":false,"spotted":false,"lookedup":true},"SFR164":{"tags":["Diode","Si"],"have":false,"want":true,"used":false,"spotted":false,"lookedup":true},"BY135":{"tags":["Diode","Si"],"have":false,"want":true,"used":false,"spotted":false,"lookedup":true},"OA210":{"tags":["Diode","Si"],"have":false,"want":true,"used":false,"spotted":false,"lookedup":true},"CV7113":{"tags":["Diode","Si"],"have":false,"want":true,"used":false,"spotted":false,"lookedup":true},"OF160":{"tags":["Diode","Si"],"have":false,"want":true,"used":false,"spotted":false,"lookedup":true},"OF241":{"tags":["Diode","Si"],"have":false,"want":true,"used":false,"spotted":false,"lookedup":true},"BY227":{"tags":["Diode","Si"],"have":false,"want":true,"used":false,"spotted":false,"lookedup":true},"1N4006":{"tags":["Diode","Si"],"have":false,"want":true,"used":false,"spotted":false,"lookedup":true},"EM508":{"tags":["Diode","Si"],"have":false,"want":true,"used":false,"spotted":false,"lookedup":true},"BY105":{"tags":["Diode","Si"],"have":false,"want":true,"used":false,"spotted":false,"lookedup":true},"TV110":{"tags":["Diode","Si"],"have":false,"want":true,"used":false,"spotted":false,"lookedup":true},"972":{"tags":["Diode","Si"],"have":false,"want":true,"used":false,"spotted":false,"lookedup":true},"BAW52":{"tags":["Diode","Si"],"have":false,"want":true,"used":false,"spotted":false,"lookedup":true},"BY206":{"tags":["Diode","Si"],"have":false,"want":true,"used":false,"spotted":false,"lookedup":true},"BY207":{"tags":["Diode","Si"],"have":false,"want":true,"used":false,"spotted":false,"lookedup":true},"TD702":{"tags":["Diode","Si"],"have":false,"want":true,"used":false,"spotted":false,"lookedup":true},"BAV19":{"tags":["Diode","Si"],"have":false,"want":true,"used":false,"spotted":false,"lookedup":true},"BA158":{"tags":["Diode","Si"],"have":false,"want":true,"used":false,"spotted":false,"lookedup":true},"BA157":{"tags":["Diode","Si"],"have":false,"want":true,"used":false,"spotted":false,"lookedup":true},"10D-4":{"tags":["Diode","Si"],"have":false,"want":true,"used":false,"spotted":false,"lookedup":true},"SR1HM-8":{"tags":["Diode","Si"],"have":false,"want":true,"used":false,"spotted":false,"lookedup":true},"SR1K-8":{"tags":["Diode","Si"],"have":false,"want":true,"used":false,"spotted":false,"lookedup":true},"TD041":{"tags":["Diode","Si"],"have":false,"want":true,"used":false,"spotted":false,"lookedup":true},"TD176":{"tags":["Diode","Si"],"have":false,"want":true,"used":false,"spotted":false,"lookedup":true},"TD190":{"tags":["Diode","Si"],"have":false,"want":true,"used":false,"spotted":false,"lookedup":true},"S1R60":{"tags":["Diode","Si"],"have":false,"want":true,"used":false,"spotted":false,"lookedup":true},"UF4004":{"tags":["Diode","Si"],"have":false,"want":true,"used":false,"spotted":false,"lookedup":true},"1N4005":{"tags":["Diode","Si"],"have":false,"want":true,"used":false,"spotted":false,"lookedup":true},"EM506":{"tags":["Diode","Si"],"have":false,"want":true,"used":false,"spotted":false,"lookedup":true},"1N1697":{"tags":["Diode","Si"],"have":false,"want":true,"used":false,"spotted":false,"lookedup":true},"1S1944":{"tags":["Diode","Si"],"have":false,"want":true,"used":false,"spotted":false,"lookedup":true},"BY130":{"tags":["Diode","Si"],"have":false,"want":true,"used":false,"spotted":false,"lookedup":true},"BY126":{"tags":["Diode","Si"],"have":false,"want":true,"used":false,"spotted":false,"lookedup":true},"40AS":{"tags":["Diode","Si"],"have":false,"want":true,"used":false,"spotted":false,"lookedup":true},"BY134":{"tags":["Diode","Si"],"have":false,"want":true,"used":false,"spotted":false,"lookedup":true},"BY170":{"tags":["Diode","Si"],"have":false,"want":true,"used":false,"spotted":false,"lookedup":true},"BY226":{"tags":["Diode","Si"],"have":false,"want":true,"used":false,"spotted":false,"lookedup":true},"1S315":{"tags":["Diode","Si"],"have":false,"want":true,"used":false,"spotted":false,"lookedup":true},"BA200":{"tags":["Diode","Si"],"have":false,"want":true,"used":false,"spotted":false,"lookedup":false},"BA201":{"tags":["Diode","Si"],"have":false,"want":true,"used":false,"spotted":false,"lookedup":false},"BA202":{"tags":["Diode","Si"],"have":false,"want":true,"used":false,"spotted":false,"lookedup":true},"BA203":{"tags":["Diode","Si"],"have":false,"want":true,"used":false,"spotted":false,"lookedup":false},"BA317":{"tags":["Diode","Si"],"have":false,"want":true,"used":false,"spotted":false,"lookedup":true},"BA318":{"tags":["Diode","Si"],"have":false,"want":true,"used":false,"spotted":false,"lookedup":true},"1N4148":{"tags":["Diode","Si"],"have":true,"want":false,"used":false,"spotted":true,"lookedup":true},"1N4149":{"tags":["Diode","Si"],"have":false,"want":true,"used":false,"spotted":false,"lookedup":true},"1N914":{"tags":["Diode","Si"],"have":true,"want":false,"used":false,"spotted":true,"lookedup":true},"BAY43":{"tags":["Diode","Si"],"have":false,"want":true,"used":false,"spotted":false,"lookedup":true},"BAY42":{"tags":["Diode","Si"],"have":false,"want":true,"used":false,"spotted":false,"lookedup":true},"BAY41":{"tags":["Diode","Si"],"have":false,"want":true,"used":false,"spotted":false,"lookedup":true},"CDG24":{"tags":["Diode","Si"],"have":false,"want":true,"used":false,"spotted":false,"lookedup":true},"BA216":{"tags":["Diode","Si"],"have":false,"want":true,"used":false,"spotted":false,"lookedup":true},"CDG27":{"tags":["Diode","Si"],"have":false,"want":true,"used":false,"spotted":false,"lookedup":true},"CDG00":{"tags":["Diode","Si"],"have":false,"want":true,"used":false,"spotted":false,"lookedup":true},"BA100":{"tags":["Diode","Si"],"have":false,"want":true,"used":false,"spotted":false,"lookedup":true},"AD411":{"tags":["Diode","Si"],"have":false,"want":true,"used":false,"spotted":false,"lookedup":true},"BA108":{"tags":["Diode","Si"],"have":false,"want":true,"used":false,"spotted":false,"lookedup":true},"S32":{"tags":["Diode","Si"],"have":false,"want":true,"used":false,"spotted":false,"lookedup":true},"BAY17":{"tags":["Diode","Si"],"have":false,"want":true,"used":false,"spotted":false,"lookedup":true},"OA127":{"tags":["Diode","Si"],"have":false,"want":true,"used":false,"spotted":false,"lookedup":true},"BAY86":{"tags":["Diode","Si"],"have":false,"want":true,"used":false,"spotted":false,"lookedup":true},"S33":{"tags":["Diode","Si"],"have":false,"want":true,"used":false,"spotted":false,"lookedup":true},"BAY18":{"tags":["Diode","Si"],"have":false,"want":true,"used":false,"spotted":false,"lookedup":true},"OA202":{"tags":["Diode","Si"],"have":false,"want":true,"used":false,"spotted":false,"lookedup":true},"SFD86":{"tags":["Diode","Si"],"have":false,"want":true,"used":false,"spotted":false,"lookedup":true},"DA146":{"tags":["Diode","Si"],"have":false,"want":true,"used":false,"spotted":false,"lookedup":true},"BAY21":{"tags":["Diode","Si"],"have":false,"want":true,"used":false,"spotted":false,"lookedup":true},"BA145":{"tags":["Diode","Si"],"have":false,"want":true,"used":false,"spotted":false,"lookedup":true},"BAY46":{"tags":["Diode","Si"],"have":false,"want":true,"used":false,"spotted":false,"lookedup":true},"OA132":{"tags":["Diode","Si"],"have":false,"want":true,"used":false,"spotted":false,"lookedup":true},"BA105":{"tags":["Diode","Si"],"have":false,"want":true,"used":false,"spotted":false,"lookedup":true},"S35":{"tags":["Diode","Si"],"have":false,"want":true,"used":false,"spotted":false,"lookedup":true},"BAY20":{"tags":["Diode","Si"],"have":false,"want":true,"used":false,"spotted":false,"lookedup":true},"S36":{"tags":["Diode","Si"],"have":false,"want":true,"used":false,"spotted":false,"lookedup":true},"BAY45":{"tags":["Diode","Si"],"have":false,"want":true,"used":false,"spotted":false,"lookedup":true},"BAY88":{"tags":["Diode","Si"],"have":false,"want":true,"used":false,"spotted":false,"lookedup":true},"OA130":{"tags":["Diode","Si"],"have":false,"want":true,"used":false,"spotted":false,"lookedup":true},"BA104":{"tags":["Diode","Si"],"have":false,"want":true,"used":false,"spotted":false,"lookedup":true},"BAY19":{"tags":["Diode","Si"],"have":false,"want":true,"used":false,"spotted":false,"lookedup":true},"BAX16":{"tags":["Diode","Si"],"have":false,"want":true,"used":false,"spotted":false,"lookedup":true},"BAY32":{"tags":["Diode","Si"],"have":false,"want":true,"used":false,"spotted":false,"lookedup":true},"BAY33":{"tags":["Diode","Si"],"have":false,"want":true,"used":false,"spotted":false,"lookedup":true},"OA131":{"tags":["Diode","Si"],"have":false,"want":true,"used":false,"spotted":false,"lookedup":true},"SFD89":{"tags":["Diode","Si"],"have":false,"want":true,"used":false,"spotted":false,"lookedup":true},"S34":{"tags":["Diode","Si"],"have":false,"want":true,"used":false,"spotted":false,"lookedup":true},"SFD43":{"tags":["Diode","Si"],"have":false,"want":true,"used":false,"spotted":false,"lookedup":true},"BAV54":{"tags":["Diode","Si"],"have":false,"want":true,"used":false,"spotted":false,"lookedup":true},"SFD143":{"tags":["Diode","Si"],"have":false,"want":true,"used":false,"spotted":false,"lookedup":true},"SFD83":{"tags":["Diode","Si"],"have":false,"want":true,"used":false,"spotted":false,"lookedup":true},"OA129":{"tags":["Diode","Si"],"have":false,"want":true,"used":false,"spotted":false,"lookedup":true},"BAY87":{"tags":["Diode","Si"],"have":false,"want":true,"used":false,"spotted":false,"lookedup":true},"BA114":{"tags":["Diode","Si"],"have":false,"want":true,"used":false,"spotted":false,"lookedup":true},"D2":{"tags":["Diode","Si"],"have":false,"want":true,"used":false,"spotted":false,"lookedup":true},"D17":{"tags":["Diode","Si"],"have":false,"want":true,"used":false,"spotted":false,"lookedup":true},"BA130":{"tags":["Diode","Si"],"have":false,"want":true,"used":false,"spotted":false,"lookedup":true},"BAY60":{"tags":["Diode","Si"],"have":false,"want":true,"used":false,"spotted":false,"lookedup":true},"1N4009":{"tags":["Diode","Si"],"have":false,"want":true,"used":false,"spotted":false,"lookedup":true},"BA128":{"tags":["Diode","Si"],"have":false,"want":true,"used":false,"spotted":false,"lookedup":true},"CD0014":{"tags":["Diode","Si"],"have":false,"want":true,"used":false,"spotted":false,"lookedup":true},"BA147":{"tags":["Diode","Si"],"have":false,"want":true,"used":false,"spotted":true,"lookedup":true},"SA418":{"tags":["Diode","Si"],"have":false,"want":true,"used":false,"spotted":false,"lookedup":true},"SFD184":{"tags":["Diode","Si"],"have":false,"want":true,"used":false,"spotted":false,"lookedup":true},"BA127":{"tags":["Diode","Si"],"have":false,"want":true,"used":false,"spotted":false,"lookedup":true},"SFD84":{"tags":["Diode","Si"],"have":false,"want":true,"used":false,"spotted":false,"lookedup":true},"CDG22":{"tags":["Diode","Si"],"have":false,"want":true,"used":false,"spotted":false,"lookedup":true},"CDG23":{"tags":["Diode","Si"],"have":false,"want":true,"used":false,"spotted":false,"lookedup":true},"CDG25":{"tags":["Diode","Si"],"have":false,"want":true,"used":false,"spotted":false,"lookedup":true},"CDG26":{"tags":["Diode","Si"],"have":false,"want":true,"used":false,"spotted":false,"lookedup":true},"SAY16":{"tags":["Diode","Si"],"have":false,"want":true,"used":false,"spotted":false,"lookedup":true},"SAY12":{"tags":["Diode","Si"],"have":false,"want":true,"used":false,"spotted":false,"lookedup":true},"SAY17":{"tags":["Diode","Si"],"have":false,"want":true,"used":false,"spotted":false,"lookedup":true},"SFD183":{"tags":["Diode","Si"],"have":false,"want":true,"used":false,"spotted":false,"lookedup":true},"1S1555":{"tags":["Diode","Si"],"have":true,"want":false,"used":false,"spotted":true,"lookedup":true},"1S2075":{"tags":["Diode","Si"],"have":false,"want":true,"used":false,"spotted":false,"lookedup":true},"1S2076":{"tags":["Diode","Si"],"have":false,"want":true,"used":false,"spotted":false,"lookedup":true},"1S44":{"tags":["Diode","Si"],"have":false,"want":true,"used":false,"spotted":false,"lookedup":true},"1S953":{"tags":["Diode","Si"],"have":false,"want":true,"used":false,"spotted":false,"lookedup":true},"1S990":{"tags":["Diode","Si"],"have":false,"want":true,"used":false,"spotted":false,"lookedup":true},"BA164":{"tags":["Diode","Si"],"have":false,"want":true,"used":false,"spotted":false,"lookedup":true},"BA166":{"tags":["Diode","Si"],"have":false,"want":true,"used":false,"spotted":false,"lookedup":true},"BA167":{"tags":["Diode","Si"],"have":false,"want":true,"used":false,"spotted":false,"lookedup":true},"BAY61":{"tags":["Diode","Si"],"have":false,"want":true,"used":false,"spotted":false,"lookedup":true},"D377":{"tags":["Diode","Si"],"have":false,"want":true,"used":false,"spotted":false,"lookedup":true},"D473":{"tags":["Diode","Si"],"have":false,"want":true,"used":false,"spotted":false,"lookedup":true},"FD100":{"tags":["Diode","Si"],"have":false,"want":true,"used":false,"spotted":false,"lookedup":true},"KD300A":{"tags":["Diode","Si"],"have":false,"want":true,"used":false,"spotted":false,"lookedup":true},"MR21":{"tags":["Diode","Si"],"have":false,"want":true,"used":false,"spotted":false,"lookedup":true},"BA204":{"tags":["Diode","Si"],"have":false,"want":true,"used":false,"spotted":false,"lookedup":true},"OA200":{"tags":["Diode","Si"],"have":false,"want":true,"used":false,"spotted":false,"lookedup":true},"OA128":{"tags":["Diode","Si"],"have":false,"want":true,"used":false,"spotted":false,"lookedup":true},"OF156":{"tags":["Diode","Si"],"have":false,"want":true,"used":false,"spotted":false,"lookedup":true},"OF158":{"tags":["Diode","Si"],"have":false,"want":true,"used":false,"spotted":false,"lookedup":true},"BAW62":{"tags":["Diode","Si"],"have":false,"want":true,"used":false,"spotted":false,"lookedup":true},"BAW76":{"tags":["Diode","Si"],"have":false,"want":true,"used":false,"spotted":false,"lookedup":true},"OF161":{"tags":["Diode","Si"],"have":false,"want":true,"used":false,"spotted":false,"lookedup":true},"OF162":{"tags":["Diode","Si"],"have":false,"want":true,"used":false,"spotted":false,"lookedup":true},"SAY30":{"tags":["Diode","Si"],"have":false,"want":true,"used":false,"spotted":false,"lookedup":true},"SFD182":{"tags":["Diode","Si"],"have":false,"want":true,"used":false,"spotted":false,"lookedup":true},"SIS20":{"tags":["Diode","Si"],"have":false,"want":true,"used":false,"spotted":false,"lookedup":true},"SV31":{"tags":["Diode","Si"],"have":false,"want":true,"used":false,"spotted":false,"lookedup":true},"TD129":{"tags":["Diode","Si"],"have":false,"want":true,"used":false,"spotted":false,"lookedup":true},"TD147":{"tags":["Diode","Si"],"have":false,"want":true,"used":false,"spotted":false,"lookedup":true},"TD482":{"tags":["Diode","Si"],"have":false,"want":true,"used":false,"spotted":false,"lookedup":true},"WG1010A":{"tags":["Diode","Si"],"have":false,"want":true,"used":false,"spotted":false,"lookedup":true},"CD0000":{"tags":["Diode","Si"],"have":false,"want":true,"used":false,"spotted":false,"lookedup":true},"CD0021":{"tags":["Diode","Si"],"have":false,"want":true,"used":false,"spotted":false,"lookedup":true},"1N34A":{"tags":["Diode","Ge"],"have":true,"want":false,"used":true,"spotted":true,"lookedup":true},"1K34A":{"tags":["Diode","Ge"],"have":false,"want":true,"used":false,"spotted":false,"lookedup":true},"1N60":{"tags":["Diode","Ge"],"have":false,"want":true,"used":false,"spotted":true,"lookedup":true},"1K60":{"tags":["Diode","Ge"],"have":false,"want":true,"used":false,"spotted":false,"lookedup":true},"1NA4":{"tags":["Diode","Ge"],"have":false,"want":true,"used":false,"spotted":false,"lookedup":true},"1NA4G":{"tags":["Diode","Ge"],"have":false,"want":true,"used":false,"spotted":false,"lookedup":true},"1NN41":{"tags":["Diode","Ge"],"have":false,"want":true,"used":false,"spotted":false,"lookedup":true},"1NN40":{"tags":["Diode","Ge"],"have":false,"want":true,"used":false,"spotted":false,"lookedup":true},"1S1007":{"tags":["Diode","Ge"],"have":false,"want":true,"used":false,"spotted":false,"lookedup":true},"1S50":{"tags":["Diode","Ge"],"have":false,"want":true,"used":false,"spotted":false,"lookedup":true},"1T23":{"tags":["Diode","Ge"],"have":false,"want":true,"used":false,"spotted":false,"lookedup":true},"1S75":{"tags":["Diode","Ge"],"have":false,"want":true,"used":false,"spotted":false,"lookedup":true},"AA117":{"tags":["Diode","Ge"],"have":false,"want":true,"used":false,"spotted":false,"lookedup":true},"1S34":{"tags":["Diode","Ge"],"have":false,"want":true,"used":false,"spotted":false,"lookedup":true},"AA103":{"tags":["Diode","Ge"],"have":false,"want":true,"used":false,"spotted":false,"lookedup":true},"1N54":{"tags":["Diode","Ge"],"have":false,"want":true,"used":false,"spotted":false,"lookedup":true},"1N54A":{"tags":["Diode","Ge"],"have":false,"want":true,"used":false,"spotted":false,"lookedup":true},"AA134":{"tags":["Diode","Ge"],"have":false,"want":true,"used":false,"spotted":false,"lookedup":true},"OA174":{"tags":["Diode","Ge"],"have":false,"want":true,"used":false,"spotted":false,"lookedup":true},"2AP16":{"tags":["Diode","Ge"],"have":false,"want":true,"used":false,"spotted":false,"lookedup":true},"AA113":{"tags":["Diode","Ge"],"have":false,"want":true,"used":false,"spotted":false,"lookedup":true},"D12":{"tags":["Diode","Ge"],"have":false,"want":true,"used":false,"spotted":false,"lookedup":true},"OA90":{"tags":["Diode","Ge"],"have":false,"want":true,"used":false,"spotted":true,"lookedup":true},"AA138":{"tags":["Diode","Ge"],"have":false,"want":true,"used":false,"spotted":false,"lookedup":true},"1S80":{"tags":["Diode","Ge"],"have":false,"want":true,"used":false,"spotted":false,"lookedup":true},"D1":{"tags":["Diode","Ge"],"have":false,"want":true,"used":false,"spotted":false,"lookedup":true},"AA112":{"tags":["Diode","Ge"],"have":false,"want":true,"used":false,"spotted":false,"lookedup":true},"D14":{"tags":["Diode","Ge"],"have":false,"want":true,"used":false,"spotted":false,"lookedup":true},"SFD110":{"tags":["Diode","Ge"],"have":false,"want":true,"used":false,"spotted":false,"lookedup":true},"2AA112":{"tags":["Diode","Ge"],"have":false,"want":true,"used":false,"spotted":false,"lookedup":true},"AA114":{"tags":["Diode","Ge"],"have":false,"want":true,"used":false,"spotted":false,"lookedup":true},"AA116":{"tags":["Diode","Ge"],"have":false,"want":true,"used":false,"spotted":false,"lookedup":true},"SFD107":{"tags":["Diode","Ge"],"have":false,"want":true,"used":false,"spotted":false,"lookedup":true},"OA159":{"tags":["Diode","Ge"],"have":false,"want":true,"used":false,"spotted":false,"lookedup":true},"2AP10":{"tags":["Diode","Ge"],"have":false,"want":true,"used":false,"spotted":false,"lookedup":true},"AA137":{"tags":["Diode","Ge"],"have":false,"want":true,"used":false,"spotted":false,"lookedup":true},"GW40":{"tags":["Diode","Ge"],"have":false,"want":true,"used":false,"spotted":false,"lookedup":true},"1N69":{"tags":["Diode","Ge"],"have":false,"want":true,"used":false,"spotted":false,"lookedup":true},"BH60":{"tags":["Diode","Ge"],"have":false,"want":true,"used":false,"spotted":false,"lookedup":true},"CK705":{"tags":["Diode","Ge"],"have":false,"want":true,"used":false,"spotted":false,"lookedup":true},"DS60":{"tags":["Diode","Ge"],"have":false,"want":true,"used":false,"spotted":false,"lookedup":true},"DS70":{"tags":["Diode","Ge"],"have":false,"want":true,"used":false,"spotted":false,"lookedup":true},"DS61":{"tags":["Diode","Ge"],"have":false,"want":true,"used":false,"spotted":false,"lookedup":true},"GW60":{"tags":["Diode","Ge"],"have":false,"want":true,"used":false,"spotted":false,"lookedup":true},"1N65":{"tags":["Diode","Ge"],"have":false,"want":true,"used":false,"spotted":false,"lookedup":true},"GW80":{"tags":["Diode","Ge"],"have":false,"want":true,"used":false,"spotted":false,"lookedup":true},"1N38":{"tags":["Diode","Ge"],"have":false,"want":true,"used":false,"spotted":false,"lookedup":true},"1N70":{"tags":["Diode","Ge"],"have":false,"want":true,"used":false,"spotted":false,"lookedup":true},"BH80":{"tags":["Diode","Ge"],"have":false,"want":true,"used":false,"spotted":false,"lookedup":true},"M3100":{"tags":["Diode","Ge"],"have":false,"want":true,"used":false,"spotted":false,"lookedup":true},"M6100":{"tags":["Diode","Ge"],"have":false,"want":true,"used":false,"spotted":false,"lookedup":true},"OA61":{"tags":["Diode","Ge"],"have":false,"want":true,"used":false,"spotted":false,"lookedup":true},"OA71":{"tags":["Diode","Ge"],"have":false,"want":true,"used":false,"spotted":false,"lookedup":true},"RL143":{"tags":["Diode","Ge"],"have":false,"want":true,"used":false,"spotted":false,"lookedup":true},"M550":{"tags":["Diode","Ge"],"have":false,"want":true,"used":false,"spotted":false,"lookedup":true},"OA50":{"tags":["Diode","Ge"],"have":false,"want":true,"used":false,"spotted":false,"lookedup":true},"RL131":{"tags":["Diode","Ge"],"have":false,"want":true,"used":false,"spotted":false,"lookedup":true},"OA73":{"tags":["Diode","Ge"],"have":false,"want":true,"used":false,"spotted":false,"lookedup":true},"1N87G":{"tags":["Diode","Ge"],"have":false,"want":true,"used":false,"spotted":false,"lookedup":true},"RL32G":{"tags":["Diode","Ge"],"have":false,"want":true,"used":false,"spotted":false,"lookedup":true},"RL32":{"tags":["Diode","Ge"],"have":false,"want":true,"used":false,"spotted":false,"lookedup":true},"EFD106":{"tags":["Diode","Ge"],"have":false,"want":true,"used":false,"spotted":false,"lookedup":true},"SFD106":{"tags":["Diode","Ge"],"have":false,"want":true,"used":false,"spotted":false,"lookedup":true},"SFD112":{"tags":["Diode","Ge"],"have":false,"want":true,"used":false,"spotted":false,"lookedup":true},"RL41G":{"tags":["Diode","Ge"],"have":false,"want":true,"used":false,"spotted":false,"lookedup":true},"SFD105":{"tags":["Diode","Ge"],"have":false,"want":true,"used":false,"spotted":false,"lookedup":true},"AA121":{"tags":["Diode","Ge"],"have":false,"want":true,"used":false,"spotted":false,"lookedup":true},"AA123":{"tags":["Diode","Ge"],"have":false,"want":true,"used":false,"spotted":false,"lookedup":true},"AA143":{"tags":["Diode","Ge"],"have":false,"want":true,"used":false,"spotted":true,"lookedup":true},"AAY21":{"tags":["Diode","Ge"],"have":false,"want":true,"used":false,"spotted":false,"lookedup":true},"MR1":{"tags":["Diode","Ge"],"have":false,"want":true,"used":false,"spotted":false,"lookedup":true},"OA160":{"tags":["Diode","Ge"],"have":false,"want":true,"used":false,"spotted":false,"lookedup":true},"OA1160":{"tags":["Diode","Ge"],"have":false,"want":true,"used":false,"spotted":false,"lookedup":true},"1N60P":{"tags":["Diode","Ge"],"have":false,"want":true,"used":false,"spotted":false,"lookedup":true},"2AA113":{"tags":["Diode","Ge"],"have":false,"want":true,"used":false,"spotted":false,"lookedup":true},"K5\/2":{"tags":["Diode","Ge"],"have":false,"want":true,"used":false,"spotted":false,"lookedup":true},"G5\/2":{"tags":["Diode","Ge"],"have":false,"want":true,"used":false,"spotted":false,"lookedup":true},"GSD5\/2":{"tags":["Diode","Ge"],"have":false,"want":true,"used":false,"spotted":false,"lookedup":true},"OA79":{"tags":["Diode","Ge"],"have":false,"want":true,"used":false,"spotted":false,"lookedup":true},"1G95":{"tags":["Diode","Ge"],"have":false,"want":true,"used":false,"spotted":false,"lookedup":true},"2AP13":{"tags":["Diode","Ge"],"have":false,"want":true,"used":false,"spotted":false,"lookedup":true},"2AP14":{"tags":["Diode","Ge"],"have":false,"want":true,"used":false,"spotted":false,"lookedup":true},"40P1":{"tags":["Diode","Ge"],"have":false,"want":true,"used":false,"spotted":false,"lookedup":true},"41P1":{"tags":["Diode","Ge"],"have":false,"want":true,"used":false,"spotted":false,"lookedup":true},"AA111":{"tags":["Diode","Ge"],"have":false,"want":true,"used":false,"spotted":false,"lookedup":true},"AM32":{"tags":["Diode","Ge"],"have":false,"want":true,"used":false,"spotted":false,"lookedup":true},"DS81":{"tags":["Diode","Ge"],"have":false,"want":true,"used":false,"spotted":false,"lookedup":true},"GEX34":{"tags":["Diode","Ge"],"have":false,"want":true,"used":false,"spotted":false,"lookedup":true},"GSD5\/105":{"tags":["Diode","Ge"],"have":false,"want":true,"used":false,"spotted":false,"lookedup":true},"K5\/105":{"tags":["Diode","Ge"],"have":false,"want":true,"used":false,"spotted":false,"lookedup":true},"OA172":{"tags":["Diode","Ge"],"have":false,"want":true,"used":false,"spotted":false,"lookedup":true},"OA1172":{"tags":["Diode","Ge"],"have":false,"want":true,"used":false,"spotted":false,"lookedup":true},"SFD115":{"tags":["Diode","Ge"],"have":false,"want":true,"used":false,"spotted":false,"lookedup":true},"SFD111":{"tags":["Diode","Ge"],"have":false,"want":true,"used":false,"spotted":false,"lookedup":true},"RL232G":{"tags":["Diode","Ge"],"have":false,"want":true,"used":false,"spotted":false,"lookedup":true},"RL232":{"tags":["Diode","Ge"],"have":false,"want":true,"used":false,"spotted":false,"lookedup":true},"RL232B":{"tags":["Diode","Ge"],"have":false,"want":true,"used":false,"spotted":false,"lookedup":true},"RL232Z":{"tags":["Diode","Ge"],"have":false,"want":true,"used":false,"spotted":false,"lookedup":true},"OA179":{"tags":["Diode","Ge"],"have":false,"want":true,"used":false,"spotted":false,"lookedup":true},"OA180":{"tags":["Diode","Ge"],"have":false,"want":true,"used":false,"spotted":false,"lookedup":true},"OA7":{"tags":["Diode","Ge"],"have":false,"want":true,"used":false,"spotted":true,"lookedup":true},"WN5458":{"tags":["Diode","Ge"],"have":false,"want":true,"used":false,"spotted":false,"lookedup":true},"OA5":{"tags":["Diode","Ge"],"have":false,"want":true,"used":false,"spotted":false,"lookedup":true},"OA6":{"tags":["Diode","Ge"],"have":false,"want":true,"used":false,"spotted":false,"lookedup":true},"TD1101":{"tags":["Diode","Ge"],"have":false,"want":true,"used":false,"spotted":false,"lookedup":true},"AN1101":{"tags":["Diode","Ge"],"have":false,"want":true,"used":false,"spotted":false,"lookedup":true},"AA139":{"tags":["Diode","Ge"],"have":false,"want":true,"used":false,"spotted":false,"lookedup":true},"SFD021":{"tags":["Diode","Ge"],"have":false,"want":true,"used":false,"spotted":false,"lookedup":true},"OA47":{"tags":["Diode","Ge"],"have":false,"want":true,"used":false,"spotted":false,"lookedup":true},"SFD037":{"tags":["Diode","Ge"],"have":false,"want":true,"used":false,"spotted":false,"lookedup":true},"OA1180":{"tags":["Diode","Ge"],"have":false,"want":true,"used":false,"spotted":false,"lookedup":true},"AA135":{"tags":["Diode","Ge"],"have":false,"want":true,"used":false,"spotted":false,"lookedup":true},"SFD127":{"tags":["Diode","Ge"],"have":false,"want":true,"used":false,"spotted":false,"lookedup":true},"OA9":{"tags":["Diode","Ge"],"have":false,"want":true,"used":false,"spotted":false,"lookedup":true},"AA136":{"tags":["Diode","Ge"],"have":false,"want":true,"used":false,"spotted":false,"lookedup":true},"1N56":{"tags":["Diode","Ge"],"have":false,"want":true,"used":false,"spotted":false,"lookedup":true},"1N56A":{"tags":["Diode","Ge"],"have":false,"want":true,"used":false,"spotted":false,"lookedup":true},"AAZ17":{"tags":["Diode","Ge"],"have":false,"want":true,"used":false,"spotted":false,"lookedup":true},"OA182":{"tags":["Diode","Ge"],"have":false,"want":true,"used":false,"spotted":false,"lookedup":true},"1N270":{"tags":["Diode","Ge"],"have":true,"want":false,"used":true,"spotted":true,"lookedup":true},"AAZ15":{"tags":["Diode","Ge"],"have":false,"want":true,"used":false,"spotted":false,"lookedup":true},"GAY64":{"tags":["Diode","Ge"],"have":false,"want":true,"used":false,"spotted":false,"lookedup":true},"OA780":{"tags":["Diode","Ge"],"have":false,"want":true,"used":false,"spotted":false,"lookedup":true},"OA720":{"tags":["Diode","Ge"],"have":false,"want":true,"used":false,"spotted":false,"lookedup":true},"GAY60":{"tags":["Diode","Ge"],"have":false,"want":true,"used":false,"spotted":false,"lookedup":true},"OA721":{"tags":["Diode","Ge"],"have":false,"want":true,"used":false,"spotted":false,"lookedup":true},"GAY61":{"tags":["Diode","Ge"],"have":false,"want":true,"used":false,"spotted":false,"lookedup":true},"GAY62":{"tags":["Diode","Ge"],"have":false,"want":true,"used":false,"spotted":false,"lookedup":true},"OA741":{"tags":["Diode","Ge"],"have":false,"want":true,"used":false,"spotted":false,"lookedup":true},"GAY63":{"tags":["Diode","Ge"],"have":false,"want":true,"used":false,"spotted":false,"lookedup":true},"OA1182":{"tags":["Diode","Ge"],"have":false,"want":true,"used":false,"spotted":false,"lookedup":true},"AAY14":{"tags":["Diode","Ge"],"have":false,"want":true,"used":false,"spotted":false,"lookedup":true},"RL52":{"tags":["Diode","Ge"],"have":false,"want":true,"used":false,"spotted":false,"lookedup":true},"OA72":{"tags":["Diode","Ge"],"have":false,"want":true,"used":false,"spotted":false,"lookedup":true},"2AP15":{"tags":["Diode","Ge"],"have":false,"want":true,"used":false,"spotted":false,"lookedup":true},"OA51":{"tags":["Diode","Ge"],"have":false,"want":true,"used":false,"spotted":false,"lookedup":true},"AA118":{"tags":["Diode","Ge"],"have":false,"want":true,"used":false,"spotted":false,"lookedup":true},"1N57":{"tags":["Diode","Ge"],"have":false,"want":true,"used":false,"spotted":false,"lookedup":true},"36D22":{"tags":["Diode","Ge"],"have":false,"want":true,"used":false,"spotted":false,"lookedup":true},"AA132":{"tags":["Diode","Ge"],"have":false,"want":true,"used":false,"spotted":false,"lookedup":true},"O401":{"tags":["Diode","Ge"],"have":false,"want":true,"used":false,"spotted":false,"lookedup":true},"RL44G":{"tags":["Diode","Ge"],"have":false,"want":true,"used":false,"spotted":false,"lookedup":true},"SFD108":{"tags":["Diode","Ge"],"have":false,"want":true,"used":false,"spotted":false,"lookedup":true},"OA161":{"tags":["Diode","Ge"],"have":false,"want":true,"used":false,"spotted":false,"lookedup":true},"2AP4":{"tags":["Diode","Ge"],"have":false,"want":true,"used":false,"spotted":false,"lookedup":true},"GW120":{"tags":["Diode","Ge"],"have":false,"want":true,"used":false,"spotted":false,"lookedup":true},"1N55":{"tags":["Diode","Ge"],"have":false,"want":true,"used":false,"spotted":false,"lookedup":true},"1N55A":{"tags":["Diode","Ge"],"have":false,"want":true,"used":false,"spotted":false,"lookedup":true},"1N75":{"tags":["Diode","Ge"],"have":false,"want":true,"used":false,"spotted":false,"lookedup":true},"DS62":{"tags":["Diode","Ge"],"have":false,"want":true,"used":false,"spotted":false,"lookedup":true},"DS621":{"tags":["Diode","Ge"],"have":false,"want":true,"used":false,"spotted":false,"lookedup":true},"M2150":{"tags":["Diode","Ge"],"have":false,"want":true,"used":false,"spotted":false,"lookedup":true},"OA1161":{"tags":["Diode","Ge"],"have":false,"want":true,"used":false,"spotted":false,"lookedup":true},"SD34":{"tags":["Diode","Ge"],"have":false,"want":true,"used":false,"spotted":false,"lookedup":true},"RL247G":{"tags":["Diode","Ge"],"have":false,"want":true,"used":false,"spotted":false,"lookedup":true},"AA133":{"tags":["Diode","Ge"],"have":false,"want":true,"used":false,"spotted":false,"lookedup":true},"1S33":{"tags":["Diode","Ge"],"have":false,"want":true,"used":false,"spotted":false,"lookedup":true},"1S446":{"tags":["Diode","Ge"],"have":false,"want":true,"used":false,"spotted":false,"lookedup":true},"1T22":{"tags":["Diode","Ge"],"have":false,"want":true,"used":false,"spotted":false,"lookedup":true},"OF173":{"tags":["Diode","Ge"],"have":false,"want":true,"used":false,"spotted":false,"lookedup":true},"AA120":{"tags":["Diode","Ge"],"have":false,"want":true,"used":false,"spotted":false,"lookedup":true},"AA127":{"tags":["Diode","Ge"],"have":false,"want":true,"used":false,"spotted":false,"lookedup":true},"OA150":{"tags":["Diode","Ge"],"have":false,"want":true,"used":false,"spotted":false,"lookedup":true},"2AP17":{"tags":["Diode","Ge"],"have":false,"want":true,"used":false,"spotted":false,"lookedup":true},"2AP5":{"tags":["Diode","Ge"],"have":false,"want":true,"used":false,"spotted":false,"lookedup":true},"\u04141\u0414":{"tags":["Diode","Ge"],"have":false,"want":true,"used":false,"spotted":false,"lookedup":true},"\u04141\u0411":{"tags":["Diode","Ge"],"have":false,"want":true,"used":false,"spotted":false,"lookedup":true},"\u04141\u0413":{"tags":["Diode","Ge"],"have":false,"want":true,"used":false,"spotted":false,"lookedup":true},"OA1150":{"tags":["Diode","Ge"],"have":false,"want":true,"used":false,"spotted":false,"lookedup":true},"OA81":{"tags":["Diode","Ge"],"have":false,"want":true,"used":false,"spotted":true,"lookedup":true},"MF5336":{"tags":["Diode","Ge"],"have":false,"want":true,"used":false,"spotted":false,"lookedup":true},"1G21":{"tags":["Diode","Ge"],"have":false,"want":true,"used":false,"spotted":false,"lookedup":true},"CG62H":{"tags":["Diode","Ge"],"have":false,"want":true,"used":false,"spotted":false,"lookedup":true},"CG61H":{"tags":["Diode","Ge"],"have":false,"want":true,"used":false,"spotted":false,"lookedup":true},"CV448":{"tags":["Diode","Ge"],"have":false,"want":true,"used":false,"spotted":false,"lookedup":true},"CG4E":{"tags":["Diode","Ge"],"have":false,"want":true,"used":false,"spotted":false,"lookedup":true},"GEX54":{"tags":["Diode","Ge"],"have":false,"want":true,"used":false,"spotted":false,"lookedup":true},"GEX55":{"tags":["Diode","Ge"],"have":false,"want":true,"used":false,"spotted":false,"lookedup":true},"GEX23":{"tags":["Diode","Ge"],"have":false,"want":true,"used":false,"spotted":false,"lookedup":true},"CV1353":{"tags":["Diode","Ge"],"have":false,"want":true,"used":false,"spotted":false,"lookedup":true},"OA85":{"tags":["Diode","Ge"],"have":false,"want":true,"used":false,"spotted":false,"lookedup":true},"OA86C":{"tags":["Diode","Ge"],"have":false,"want":true,"used":false,"spotted":false,"lookedup":true},"1G22":{"tags":["Diode","Ge"],"have":false,"want":true,"used":false,"spotted":false,"lookedup":true},"39P1":{"tags":["Diode","Ge"],"have":false,"want":true,"used":false,"spotted":false,"lookedup":true},"1N39":{"tags":["Diode","Ge"],"have":false,"want":true,"used":false,"spotted":false,"lookedup":true},"AM31":{"tags":["Diode","Ge"],"have":false,"want":true,"used":false,"spotted":false,"lookedup":true},"B-2B":{"tags":["Diode","Ge"],"have":false,"want":true,"used":false,"spotted":false,"lookedup":true},"CV1354":{"tags":["Diode","Ge"],"have":false,"want":true,"used":false,"spotted":false,"lookedup":true},"OA86":{"tags":["Diode","Ge"],"have":false,"want":true,"used":false,"spotted":false,"lookedup":true},"OA87":{"tags":["Diode","Ge"],"have":false,"want":true,"used":false,"spotted":false,"lookedup":true},"OA91":{"tags":["Diode","Ge"],"have":false,"want":true,"used":false,"spotted":true,"lookedup":true},"CV7130":{"tags":["Diode","Ge"],"have":false,"want":true,"used":false,"spotted":false,"lookedup":true},"RL43G":{"tags":["Diode","Ge"],"have":false,"want":true,"used":false,"spotted":false,"lookedup":true},"RL34G":{"tags":["Diode","Ge"],"have":false,"want":true,"used":false,"spotted":false,"lookedup":true},"RL116":{"tags":["Diode","Ge"],"have":false,"want":true,"used":false,"spotted":false,"lookedup":true},"OA95":{"tags":["Diode","Ge"],"have":false,"want":true,"used":false,"spotted":false,"lookedup":true},"1T33":{"tags":["Diode","Ge"],"have":false,"want":true,"used":false,"spotted":false,"lookedup":true},"1T26":{"tags":["Diode","Ge"],"have":false,"want":true,"used":false,"spotted":false,"lookedup":true},"MA80":{"tags":["Diode","Ge"],"have":false,"want":true,"used":false,"spotted":false,"lookedup":true},"MA51A":{"tags":["Diode","Ge"],"have":false,"want":true,"used":false,"spotted":false,"lookedup":true},"MA51":{"tags":["Diode","Ge"],"have":false,"want":true,"used":false,"spotted":false,"lookedup":true},"SD46":{"tags":["Diode","Ge"],"have":false,"want":true,"used":false,"spotted":false,"lookedup":true},"SFD113":{"tags":["Diode","Ge"],"have":false,"want":true,"used":false,"spotted":false,"lookedup":true},"SFD104":{"tags":["Diode","Ge"],"have":false,"want":true,"used":false,"spotted":false,"lookedup":true},"SD6":{"tags":["Diode","Ge"],"have":false,"want":true,"used":false,"spotted":false,"lookedup":true},"1N295":{"tags":["Diode","Ge"],"have":false,"want":true,"used":false,"spotted":false,"lookedup":true},"1N64":{"tags":["Diode","Ge"],"have":false,"want":true,"used":false,"spotted":false,"lookedup":true},"CK706":{"tags":["Diode","Ge"],"have":false,"want":true,"used":false,"spotted":false,"lookedup":true},"DR117":{"tags":["Diode","Ge"],"have":false,"want":true,"used":false,"spotted":false,"lookedup":true},"CK706A":{"tags":["Diode","Ge"],"have":false,"want":true,"used":false,"spotted":false,"lookedup":true},"GW20":{"tags":["Diode","Ge"],"have":false,"want":true,"used":false,"spotted":false,"lookedup":true},"BH30":{"tags":["Diode","Ge"],"have":false,"want":true,"used":false,"spotted":false,"lookedup":true},"DS604":{"tags":["Diode","Ge"],"have":false,"want":true,"used":false,"spotted":false,"lookedup":true},"M820":{"tags":["Diode","Ge"],"have":false,"want":true,"used":false,"spotted":false,"lookedup":true},"OA60":{"tags":["Diode","Ge"],"have":false,"want":true,"used":false,"spotted":false,"lookedup":true},"RL133":{"tags":["Diode","Ge"],"have":false,"want":true,"used":false,"spotted":false,"lookedup":true},"ED16":{"tags":["Diode","Ge"],"have":false,"want":true,"used":false,"spotted":false,"lookedup":true},"DOG52":{"tags":["Diode","Ge"],"have":false,"want":true,"used":false,"spotted":false,"lookedup":true},"RS1811":{"tags":["Diode","Ge"],"have":false,"want":true,"used":false,"spotted":false,"lookedup":true},"AA119":{"tags":["Diode","Ge"],"have":false,"want":true,"used":false,"spotted":false,"lookedup":true},"NTE109":{"tags":["Diode","Ge"],"have":false,"want":true,"used":false,"spotted":false,"lookedup":true},"AA227":{"tags":["Diode","Ge"],"have":false,"want":true,"used":false,"spotted":false,"lookedup":true},"AAP152":{"tags":["Diode","Ge"],"have":false,"want":true,"used":false,"spotted":false,"lookedup":true},"AAP153":{"tags":["Diode","Ge"],"have":false,"want":true,"used":false,"spotted":true,"lookedup":true},"AA110":{"tags":["Diode","Ge"],"have":false,"want":true,"used":false,"spotted":false,"lookedup":true},"2AP3":{"tags":["Diode","Ge"],"have":false,"want":true,"used":false,"spotted":false,"lookedup":true},"MD34":{"tags":["Diode","Ge"],"have":false,"want":true,"used":false,"spotted":false,"lookedup":true},"MD60":{"tags":["Diode","Ge"],"have":false,"want":true,"used":false,"spotted":false,"lookedup":true},"1N60A":{"tags":["Diode","Ge"],"have":false,"want":true,"used":false,"spotted":false,"lookedup":true},"1NA9":{"tags":["Diode","Ge"],"have":false,"want":true,"used":false,"spotted":false,"lookedup":true},"1N60C":{"tags":["Diode","Ge"],"have":false,"want":true,"used":false,"spotted":false,"lookedup":true},"OA70":{"tags":["Diode","Ge"],"have":false,"want":true,"used":false,"spotted":false,"lookedup":true},"17P1":{"tags":["Diode","Ge"],"have":false,"want":true,"used":false,"spotted":false,"lookedup":true},"2AP9":{"tags":["Diode","Ge"],"have":false,"want":true,"used":false,"spotted":false,"lookedup":true},"1Z1":{"tags":["Diode","Ge"],"have":false,"want":true,"used":false,"spotted":false,"lookedup":true},"1S188":{"tags":["Diode","Ge"],"have":false,"want":true,"used":false,"spotted":false,"lookedup":true},"2AK1":{"tags":["Diode","Ge"],"have":false,"want":true,"used":false,"spotted":false,"lookedup":true},"2AP":{"tags":["Diode","Ge"],"have":false,"want":true,"used":false,"spotted":false,"lookedup":true},"RL31":{"tags":["Diode","Ge"],"have":false,"want":true,"used":false,"spotted":false,"lookedup":true},"RL41":{"tags":["Diode","Ge"],"have":false,"want":true,"used":false,"spotted":false,"lookedup":true},"WN5457":{"tags":["Diode","Ge"],"have":false,"want":true,"used":false,"spotted":false,"lookedup":true},"93B27-1":{"tags":["Diode","Ge"],"have":false,"want":true,"used":false,"spotted":false,"lookedup":true},"AAY27":{"tags":["Diode","Ge"],"have":false,"want":true,"used":false,"spotted":false,"lookedup":true},"MO-60":{"tags":["Diode","Ge"],"have":false,"want":true,"used":false,"spotted":false,"lookedup":true},"1N34":{"tags":["Diode","Ge"],"have":false,"want":true,"used":false,"spotted":false,"lookedup":true},"BAT41":{"tags":["Diode","Schottky","Si"],"have":true,"want":false,"used":true,"spotted":true,"lookedup":false},"\u04149\u0415":{"tags":["Diode","Ge"],"have":true,"want":false,"used":false,"spotted":true,"lookedup":false},"\u04149\u0411":{"tags":["Diode","Ge"],"have":true,"want":false,"used":false,"spotted":true,"lookedup":false},"\u041418":{"tags":["Diode","Ge"],"have":false,"want":true,"used":false,"spotted":true,"lookedup":true},"BAT46":{"tags":["Diode","Schottky","Si"],"have":false,"want":true,"used":false,"spotted":true,"lookedup":false},"GA100":{"tags":["Diode","Ge"],"have":false,"want":true,"used":false,"spotted":false,"lookedup":true},"DOG53":{"tags":["Diode","Ge"],"have":false,"want":true,"used":false,"spotted":false,"lookedup":true},"OA625":{"tags":["Diode","Ge"],"have":false,"want":true,"used":false,"spotted":false,"lookedup":true},"GE-DET":{"tags":["Diode","Ge"],"have":false,"want":true,"used":false,"spotted":false,"lookedup":true},"OA645":{"tags":["Diode","Ge"],"have":false,"want":true,"used":false,"spotted":false,"lookedup":true},"GA101":{"tags":["Diode","Ge"],"have":false,"want":true,"used":false,"spotted":false,"lookedup":true},"\u04149":{"tags":["Diode","Ge"],"have":false,"want":true,"used":false,"spotted":false,"lookedup":true},"GA102":{"tags":["Diode","Ge"],"have":false,"want":true,"used":false,"spotted":true,"lookedup":true},"OA665":{"tags":["Diode","Ge"],"have":false,"want":true,"used":false,"spotted":false,"lookedup":true},"GA104":{"tags":["Diode","Ge"],"have":false,"want":true,"used":false,"spotted":false,"lookedup":true},"OA705":{"tags":["Diode","Ge"],"have":false,"want":true,"used":false,"spotted":false,"lookedup":true},"\u04142\u0415":{"tags":["Diode","Ge"],"have":false,"want":true,"used":false,"spotted":false,"lookedup":true},"\u04142\u0416\u0412\u041f":{"tags":["Diode","Ge"],"have":false,"want":true,"used":false,"spotted":false,"lookedup":true},"\u04149\u0412":{"tags":["Diode","Ge"],"have":false,"want":true,"used":false,"spotted":false,"lookedup":true},"BAT54":{"tags":["Diode","Schottky","Si"],"have":false,"want":true,"used":false,"spotted":true,"lookedup":false},"BAT85":{"tags":["Diode","Schottky","Si"],"have":false,"want":true,"used":false,"spotted":true,"lookedup":true},"BAT43":{"tags":["Diode","Schottky","Si"],"have":false,"want":true,"used":false,"spotted":false,"lookedup":true},"BAT42":{"tags":["Diode","Schottky","Si"],"have":false,"want":true,"used":false,"spotted":false,"lookedup":true},"BA102":{"tags":["Diode","Si","Varicap"],"have":false,"want":true,"used":false,"spotted":true,"lookedup":true},"BA101":{"tags":["Diode","Si","Varicap"],"have":false,"want":true,"used":false,"spotted":false,"lookedup":true},"OA910":{"tags":["Diode","Si","Varicap"],"have":false,"want":true,"used":false,"spotted":false,"lookedup":true},"1S85":{"tags":["Diode","Si","Varicap"],"have":false,"want":true,"used":false,"spotted":false,"lookedup":true},"BA109":{"tags":["Diode","Si","Varicap"],"have":false,"want":true,"used":false,"spotted":false,"lookedup":true},"ITT410":{"tags":["Diode","Si","Varicap"],"have":false,"want":true,"used":false,"spotted":false,"lookedup":true},"BB119":{"tags":["Diode","Si","Varicap"],"have":false,"want":true,"used":false,"spotted":true,"lookedup":true},"1S145":{"tags":["Diode","Si","Varicap"],"have":false,"want":true,"used":false,"spotted":false,"lookedup":true},"BA124":{"tags":["Diode","Si","Varicap"],"have":false,"want":true,"used":false,"spotted":false,"lookedup":true},"1S352":{"tags":["Diode","Si","Varicap"],"have":false,"want":true,"used":false,"spotted":false,"lookedup":true},"1S49":{"tags":["Diode","Si","Varicap"],"have":false,"want":true,"used":false,"spotted":false,"lookedup":true},"BA111":{"tags":["Diode","Si","Varicap"],"have":false,"want":true,"used":false,"spotted":false,"lookedup":true},"SMV709":{"tags":["Diode","Si","Varicap"],"have":false,"want":true,"used":false,"spotted":false,"lookedup":true},"BA150":{"tags":["Diode","Si","Varicap"],"have":false,"want":true,"used":false,"spotted":false,"lookedup":true},"BA138":{"tags":["Diode","Si","Varicap"],"have":false,"want":true,"used":false,"spotted":false,"lookedup":true},"BA125":{"tags":["Diode","Si","Varicap"],"have":false,"want":true,"used":false,"spotted":false,"lookedup":true},"1N266":{"tags":["Diode","Ge"],"have":false,"want":true,"used":false,"spotted":true,"lookedup":false},"BA282":{"tags":["Diode","Si"],"have":false,"want":true,"used":false,"spotted":true,"lookedup":false},"BA283":{"tags":["Diode","Si"],"have":false,"want":true,"used":false,"spotted":true,"lookedup":false},"BA300":{"tags":["Diode","Si"],"have":false,"want":true,"used":false,"spotted":true,"lookedup":false},"\u0414310":{"tags":["Diode","Ge"],"have":false,"want":true,"used":false,"spotted":true,"lookedup":true},"\u0413\u0414507\u0410":{"tags":["Diode","Ge"],"have":false,"want":true,"used":false,"spotted":false,"lookedup":false},"1\u0414507\u0410":{"tags":["Diode","Ge"],"have":false,"want":true,"used":false,"spotted":true,"lookedup":false},"\u041a\u0414521\u0410":{"tags":["Diode","Si"],"have":false,"want":true,"used":false,"spotted":true,"lookedup":true},"1N695":{"tags":["Diode","Ge"],"have":false,"want":true,"used":false,"spotted":true,"lookedup":true},"1N781":{"tags":["Diode","Ge"],"have":false,"want":true,"used":false,"spotted":true,"lookedup":false},"MA856":{"tags":["Diode","Si"],"have":false,"want":true,"used":false,"spotted":true,"lookedup":false},"1S1588":{"tags":["Diode","Si"],"have":false,"want":true,"used":false,"spotted":true,"lookedup":true},"1N916":{"tags":["Diode","Si"],"have":false,"want":true,"used":false,"spotted":true,"lookedup":true},"1N993":{"tags":["Diode","Ge"],"have":false,"want":true,"used":false,"spotted":true,"lookedup":false},"OA1154":{"tags":["Diode","Ge"],"have":false,"want":true,"used":false,"spotted":true,"lookedup":true},"OA154":{"tags":["Diode","Ge"],"have":false,"want":true,"used":false,"spotted":false,"lookedup":true},"OA154Q":{"tags":["Diode","Ge"],"have":false,"want":true,"used":false,"spotted":false,"lookedup":true},"OA1154Q":{"tags":["Diode","Ge"],"have":false,"want":true,"used":false,"spotted":false,"lookedup":true},"1N3470":{"tags":["Diode","Ge"],"have":false,"want":true,"used":false,"spotted":true,"lookedup":false},"1N4448":{"tags":["Diode","Si"],"have":false,"want":true,"used":false,"spotted":true,"lookedup":true},"1N925":{"tags":["Diode","Si"],"have":false,"want":true,"used":false,"spotted":true,"lookedup":false},"1N802":{"tags":["Diode","Si"],"have":false,"want":true,"used":false,"spotted":true,"lookedup":false},"NTE177":{"tags":["Diode","Si"],"have":false,"want":true,"used":false,"spotted":false,"lookedup":false},"\u041a\u0414521\u0412":{"tags":["Diode","Si"],"have":false,"want":true,"used":false,"spotted":true,"lookedup":true},"2\u0414510\u0410":{"tags":["Diode","Si"],"have":false,"want":true,"used":false,"spotted":true,"lookedup":false},"\u041a\u0414522\u0411":{"tags":["Diode","Si"],"have":false,"want":true,"used":false,"spotted":true,"lookedup":false},"1N3575":{"tags":["Diode","Si"],"have":false,"want":true,"used":false,"spotted":false,"lookedup":false},"1N3067":{"tags":["Diode","Si"],"have":false,"want":true,"used":false,"spotted":true,"lookedup":false},"1N1219":{"tags":["Diode","Si"],"have":false,"want":true,"used":false,"spotted":false,"lookedup":false},"1N1220":{"tags":["Diode","Si"],"have":false,"want":true,"used":false,"spotted":false,"lookedup":false},"1N1473":{"tags":["Diode","Si"],"have":false,"want":true,"used":false,"spotted":false,"lookedup":false},"\u041a\u0414521\u0413":{"tags":["Diode","Si"],"have":false,"want":true,"used":false,"spotted":false,"lookedup":true},"1N904":{"tags":["Diode","Si"],"have":false,"want":true,"used":false,"spotted":false,"lookedup":false},"1N905":{"tags":["Diode","Si"],"have":false,"want":true,"used":false,"spotted":false,"lookedup":false},"1N906":{"tags":["Diode","Si"],"have":false,"want":true,"used":false,"spotted":false,"lookedup":false},"1N907":{"tags":["Diode","Si"],"have":false,"want":true,"used":false,"spotted":false,"lookedup":false},"1N6263":{"tags":["Diode","Schottky","Si"],"have":false,"want":true,"used":false,"spotted":true,"lookedup":false},"BAS16":{"tags":["Diode","Si"],"have":false,"want":true,"used":false,"spotted":true,"lookedup":false}}